MANIFEST.in
README.rst
setup.py
collective/__init__.py
collective.captchacontactinfo.egg-info/PKG-INFO
collective.captchacontactinfo.egg-info/SOURCES.txt
collective.captchacontactinfo.egg-info/dependency_links.txt
collective.captchacontactinfo.egg-info/entry_points.txt
collective.captchacontactinfo.egg-info/namespace_packages.txt
collective.captchacontactinfo.egg-info/not-zip-safe
collective.captchacontactinfo.egg-info/requires.txt
collective.captchacontactinfo.egg-info/top_level.txt
collective/captchacontactinfo/__init__.py
collective/captchacontactinfo/configure.zcml
collective/captchacontactinfo/i18n.sh
collective/captchacontactinfo/interfaces.py
collective/captchacontactinfo/setuphandlers.py
collective/captchacontactinfo/browser/__init__.py
collective/captchacontactinfo/browser/configure.zcml
collective/captchacontactinfo/browser/contact_form_view.py
collective/captchacontactinfo/browser/ajax/__init__.py
collective/captchacontactinfo/browser/ajax/configure.zcml
collective/captchacontactinfo/browser/ajax/utils.py
collective/captchacontactinfo/browser/static/css/captchacontactinfo.css
collective/captchacontactinfo/browser/static/scripts/policy_ajax.js
collective/captchacontactinfo/browser/templates/contact-info-email.pt
collective/captchacontactinfo/browser/templates/contact-info.pt
collective/captchacontactinfo/controlpanel/__init__.py
collective/captchacontactinfo/controlpanel/configure.zcml
collective/captchacontactinfo/controlpanel/interfaces.py
collective/captchacontactinfo/controlpanel/view.py
collective/captchacontactinfo/locales/collective.captchacontactinfo.pot
collective/captchacontactinfo/locales/de/LC_MESSAGES/collective.captchacontactinfo.po
collective/captchacontactinfo/locales/it/LC_MESSAGES/collective.captchacontactinfo.po
collective/captchacontactinfo/profiles/default/actions.xml
collective/captchacontactinfo/profiles/default/browserlayer.xml
collective/captchacontactinfo/profiles/default/captchacontactinfo-various.txt
collective/captchacontactinfo/profiles/default/controlpanel.xml
collective/captchacontactinfo/profiles/default/metadata.xml
collective/captchacontactinfo/profiles/default/registry.xml
collective/captchacontactinfo/profiles/uninstall/browserlayer.xml
collective/captchacontactinfo/profiles/uninstall/registry.xml
docs/HISTORY.rst
docs/LICENSE.GPL
docs/LICENSE.txt