Metadata-Version: 1.1
Name: collective.captchacontactinfo
Version: 3.0.1
Summary: A simple customization for Plone contact-info that add a validation for anonymous users
Home-page: http://plone.org/products/collective.captchacontactinfo
Author: RedTurtle Technology
Author-email: sviluppoplone@redturtle.it
License: GPL
Keywords: plone captcha e-mail contact-info
Platform: UNKNOWN
Classifier: Programming Language :: Python
Classifier: Framework :: Plone
Classifier: Framework :: Plone :: 3.3
Classifier: Framework :: Plone :: 4.0
Classifier: Framework :: Plone :: 4.1
Classifier: Framework :: Plone :: 4.2
Classifier: Framework :: Plone :: 4.3
Classifier: Development Status :: 5 - Production/Stable
Classifier: License :: OSI Approved :: GNU General Public License (GPL)
